Agent/CodeAgent.py
Agent/CodeAgentV2.py
Agent/CodeAgentV3.py
Agent/__init__.py
c4agent-1.21.dist-info/licenses/LICENSE
c4agent-1.21.dist-info/METADATA
c4agent-1.21.dist-info/WHEEL
c4agent-1.21.dist-info/top_level.txt
c4agent-1.21.dist-info/RECORD
