Metadata-Version: 2.4
Name: c4agent
Version: 1.21
Summary: A multi-provider Python code execution and dependency management agent
Author-email: Boopathi Raj <boopathiraj.researchbrains@gmail.com>
License:                                  Apache License
Project-URL: Homepage, https://github.com/rajboopathiking/codeagent
Project-URL: Bug Tracker, https://github.com/rajboopathiking/codeagent/issues
Requires-Python: >=3.8
License-File: LICENSE
Requires-Dist: requests
Requires-Dist: PyPDF2
Requires-Dist: autopep8
Requires-Dist: anthropic
Requires-Dist: openai
Requires-Dist: Pillow>=9.0.0
Requires-Dist: setuptools>=60.0.0
Requires-Dist: transformers>=4.30.0
Requires-Dist: torch>=1.12.0
Dynamic: license-file
